LICENSE
README.md
setup.py
remork/__init__.py
remork/client.py
remork/files.py
remork/process.py
remork/router.py
remork/runner.py
remork/testinfra.py
remork/utils.py
remork.egg-info/PKG-INFO
remork.egg-info/SOURCES.txt
remork.egg-info/dependency_links.txt
remork.egg-info/not-zip-safe
remork.egg-info/requires.txt
remork.egg-info/top_level.txt
tests/test_client.py
tests/test_files.py
tests/test_router.py